typed_linter/__init__.py
typed_linter/example.py
typed_linter/py.typed
typed_linter-0.0.0.dist-info/WHEEL
typed_linter-0.0.0.dist-info/METADATA
typed_linter-0.0.0.dist-info/RECORD
