Metadata-Version: 2.1
Name: typed-linter
Version: 0.0.0
Summary: Linter and code quality tool that uses real type information to find bugs and problems
Home-page: https://github.com/wemake.services/typed-linter
Requires-Python: >=3.7,<4.0
Classifier: Development Status :: 3 - Alpha
Classifier: Intended Audience :: Developers
Classifier: Operating System :: OS Independent
Classifier: Programming Language :: Python :: 3
Classifier: Programming Language :: Python :: 3.7
Classifier: Programming Language :: Python :: 3.8
Classifier: Programming Language :: Python :: 3.9
Classifier: Topic :: Software Development :: Libraries :: Python Modules
Project-URL: Repository, https://github.com/wemake.services/typed-linter
